gemmit/__init__.py
gemmit/cli.py
gemmit-0.0.1.dist-info/LICENSE
gemmit-0.0.1.dist-info/METADATA
gemmit-0.0.1.dist-info/WHEEL
gemmit-0.0.1.dist-info/entry_points.txt
gemmit-0.0.1.dist-info/RECORD
