Metadata-Version: 2.3
Name: gemmit
Version: 0.0.1
Summary: AI-powered Conventional Commit generator using Gemini
License: MIT
Author: Md Romjan Ali
Author-email: romjanvr5@gmail.com
Requires-Python: >=3.9
Classifier: License :: OSI Approved :: MIT License
Classifier: Programming Language :: Python :: 3
Classifier: Programming Language :: Python :: 3.9
Classifier: Programming Language :: Python :: 3.10
Classifier: Programming Language :: Python :: 3.11
Classifier: Programming Language :: Python :: 3.12
Classifier: Programming Language :: Python :: 3.13
